{"paths": {"admin/js/vendor/jquery/jquery.js": "admin/js/vendor/jquery/jquery.aacc43d6f308.js", "admin/js/vendor/jquery/jquery.min.js": "admin/js/vendor/jquery/jquery.min.33cabfa15c10.js", "admin/js/vendor/jquery/LICENSE-JQUERY.txt": "admin/js/vendor/jquery/LICENSE-JQUERY.a158210a2737.txt", "admin/js/vendor/xregexp/xregexp.min.js": "admin/js/vendor/xregexp/xregexp.min.c95393b8ca4d.js", "admin/js/vendor/xregexp/LICENSE-XREGEXP.txt": "admin/js/vendor/xregexp/LICENSE-XREGEXP.d64cecf4f157.txt", "admin/js/vendor/xregexp/xregexp.js": "admin/js/vendor/xregexp/xregexp.1865b1cf5085.js", "src/scss/apps/_invitations.scss": "src/scss/apps/_invitations.fc8c8bb6eb80.scss", "src/scss/apps/_notifications.scss": "src/scss/apps/_notifications.631c360f8132.scss", "src/scss/apps/_blog.scss": "src/scss/apps/_blog.1a6dbc682dc0.scss", "src/scss/apps/_account.scss": "src/scss/apps/_account.4e83faea1d61.scss", "src/scss/apps/_index.scss": "src/scss/apps/_index.2a7b17476613.scss", "src/scss/apps/_announcements.scss": "src/scss/apps/_announcements.7067c49e005d.scss", "src/scss/apps/_documents.scss": "src/scss/apps/_documents.41fc844cb050.scss", "src/scss/apps/_stripe.scss": "src/scss/apps/_stripe.81cdb07655f1.scss", "src/scss/apps/_messages.scss": "src/scss/apps/_messages.313544b76dcb.scss", "src/scss/apps/_cohorts.scss": "src/scss/apps/_cohorts.c306645b052b.scss", "src/scss/apps/_likes.scss": "src/scss/apps/_likes.51ece3a01e42.scss", "src/tests/spec/base.js": "src/tests/spec/base.9197c479d246.js", "admin/img/gis/move_vertex_off.svg": "admin/img/gis/move_vertex_off.7a23bf31ef8a.svg", "admin/img/gis/move_vertex_on.svg": "admin/img/gis/move_vertex_on.0047eba25b67.svg", "admin/js/admin/RelatedObjectLookups.js": "admin/js/admin/RelatedObjectLookups.d2bdb1018963.js", "admin/js/admin/DateTimeShortcuts.js": "admin/js/admin/DateTimeShortcuts.1536fb6bea1d.js", "src/scss/index.scss": "src/scss/index.30d52d2ebe44.scss", "src/scss/_body.scss": "src/scss/_body.4bb771f32b8a.scss", "src/scss/_config.scss": "src/scss/_config.7dc0d1142b42.scss", "src/scss/_pinax.scss": "src/scss/_pinax.db79dee1d492.scss", "src/scss/_tables.scss": "src/scss/_tables.5a8857f9c079.scss", "src/scss/_mixins.scss": "src/scss/_mixins.699067302c2e.scss", "src/scss/_forms.scss": "src/scss/_forms.e31eec2e4e21.scss", "src/scss/_externals.scss": "src/scss/_externals.44f61415dfae.scss", "src/scss/_messages.scss": "src/scss/_messages.f79ce74fba46.scss", "src/scss/_nav.scss": "src/scss/_nav.95af0e5845ce.scss", "src/scss/_errors.scss": "src/scss/_errors.5b9edf50be9f.scss", "src/fonts/glyphicons-halflings-regular.svg": "src/fonts/glyphicons-halflings-regular.89889688147b.svg", "src/fonts/glyphicons-halflings-regular.eot": "src/fonts/glyphicons-halflings-regular.f4769f9bdb74.eot", "src/fonts/glyphicons-halflings-regular.woff2": "src/fonts/glyphicons-halflings-regular.448c34a56d69.woff2", "src/fonts/glyphicons-halflings-regular.ttf": "src/fonts/glyphicons-halflings-regular.e18bbf611f2a.ttf", "src/fonts/glyphicons-halflings-regular.woff": "src/fonts/glyphicons-halflings-regular.fa2772327f55.woff", "src/js/index.js": "src/js/index.3f3788591888.js", "src/js/site.js": "src/js/site.6b468b63746a.js", "src/js/bootstrap.js": "src/js/bootstrap.fb81549ee289.js", "src/js/pinax-documents.js": "src/js/pinax-documents.82f39ff826b7.js", "src/js/messages.js": "src/js/messages.9e27d4377eab.js", "src/js/npm.js": "src/js/npm.ccb7f3909e30.js", "src/js/bootstrap.min.js": "src/js/bootstrap.min.5869c96cc8f1.js", "src/js/ajax.js": "src/js/ajax.7dd5b4a48243.js", "src/js/pinax-stripe.js": "src/js/pinax-stripe.b0cd93bae0b3.js", "src/tests/index.js": "src/tests/index.329d37857eb9.js", "src/tests/main.js": "src/tests/main.a0d8aac687e3.js", "src/tests/index.html": "src/tests/index.0b667f125800.html", "src/tests/browser.js": "src/tests/browser.8eb1decc161b.js", "src/tests/fixtures.js": "src/tests/fixtures.2945720ad40e.js", "src/css/bootstrap.css.map": "src/css/bootstrap.css.c7ffd8c7a285.map", "src/css/bootstrap-theme.min.css": "src/css/bootstrap-theme.min.ab6b02efeaf1.css", "src/css/cjap.css": "src/css/cjap.1ed17a984ef6.css", "src/css/bootstrap-theme.min.css.map": "src/css/bootstrap-theme.min.css.5f587b800215.map", "src/css/bootstrap-theme.css": "src/css/bootstrap-theme.b9b46bcc4dad.css", "src/css/bootstrap.min.css.map": "src/css/bootstrap.min.css.35b79ebe0b78.map", "src/css/bootstrap.min.css": "src/css/bootstrap.min.5c7070ef655a.css", "src/css/bootstrap.css": "src/css/bootstrap.e7aa4e830a64.css", "src/css/bootstrap-theme.css.map": "src/css/bootstrap-theme.css.d6cc0a3c7532.map", "admin/img/tooltag-arrowright.svg": "admin/img/tooltag-arrowright.bbfb788a849e.svg", "admin/img/icon-clock.svg": "admin/img/icon-clock.e1d4dfac3f2b.svg", "admin/img/search.svg": "admin/img/search.7cf54ff789c6.svg", "admin/img/README.txt": "admin/img/README.837277fa1908.txt", "admin/img/icon-alert.svg": "admin/img/icon-alert.034cc7d8a67f.svg", "admin/img/icon-calendar.svg": "admin/img/icon-calendar.ac7aea671bea.svg", "admin/img/calendar-icons.svg": "admin/img/calendar-icons.39b290681a8b.svg", "admin/img/selector-icons.svg": "admin/img/selector-icons.b4555096cea2.svg", "admin/img/LICENSE": "admin/img/LICENSE.2c54f4e1ca1c", "admin/img/icon-unknown.svg": "admin/img/icon-unknown.a18cb4398978.svg", "admin/img/sorting-icons.svg": "admin/img/sorting-icons.3a097b59f104.svg", "admin/img/tooltag-add.svg": "admin/img/tooltag-add.e59d620a9742.svg", "admin/img/inline-delete.svg": "admin/img/inline-delete.fec1b761f254.svg", "admin/img/icon-yes.svg": "admin/img/icon-yes.d2f9f035226a.svg", "admin/img/icon-no.svg": "admin/img/icon-no.439e821418cd.svg", "admin/img/icon-deletelink.svg": "admin/img/icon-deletelink.564ef9dc3854.svg", "admin/img/icon-unknown-alt.svg": "admin/img/icon-unknown-alt.81536e128bb6.svg", "admin/img/icon-addlink.svg": "admin/img/icon-addlink.d519b3bab011.svg", "admin/img/icon-changelink.svg": "admin/img/icon-changelink.18d2fd706348.svg", "admin/fonts/README.txt": "admin/fonts/README.2c3d0bcdede2.txt", "admin/fonts/Roboto-Regular-webfont.woff": "admin/fonts/Roboto-Regular-webfont.ec39515ae8c6.woff", "admin/fonts/Roboto-Light-webfont.woff": "admin/fonts/Roboto-Light-webfont.b446c2399bb6.woff", "admin/fonts/LICENSE.txt": "admin/fonts/LICENSE.d273d63619c9.txt", "admin/fonts/Roboto-Bold-webfont.woff": "admin/fonts/Roboto-Bold-webfont.2ad99072841e.woff", "admin/js/actions.js": "admin/js/actions.32861b6cbdf9.js", "admin/js/change_form.js": "admin/js/change_form.9e85003a1a38.js", "admin/js/collapse.min.js": "admin/js/collapse.min.dc930adb2821.js", "admin/js/urlify.js": "admin/js/urlify.411bc3bb651c.js", "admin/js/collapse.js": "admin/js/collapse.17d715df2104.js", "admin/js/inlines.js": "admin/js/inlines.eda404ee376d.js", "admin/js/core.js": "admin/js/core.fd861d43f0f5.js", "admin/js/inlines.min.js": "admin/js/inlines.min.d75b9ed03975.js", "admin/js/SelectBox.js": "admin/js/SelectBox.b49f008d186b.js", "admin/js/timeparse.js": "admin/js/timeparse.51258861a46a.js", "admin/js/popup_response.js": "admin/js/popup_response.6ce3197f8fc8.js", "admin/js/prepopulate.min.js": "admin/js/prepopulate.min.f4057ebb9b62.js", "admin/js/actions.min.js": "admin/js/actions.min.f51f04edab28.js", "admin/js/prepopulate_init.js": "admin/js/prepopulate_init.0d3b53c37074.js", "admin/js/cancel.js": "admin/js/cancel.1d69cba4b4bf.js", "admin/js/prepopulate.js": "admin/js/prepopulate.ff9208865444.js", "admin/js/SelectFilter2.js": "admin/js/SelectFilter2.17009b6d4428.js", "admin/js/calendar.js": "admin/js/calendar.9ac94d055fbd.js", "admin/js/jquery.init.js": "admin/js/jquery.init.95b62fa19378.js", "admin/css/fonts.css": "admin/css/fonts.494e4ec545c9.css", "admin/css/base.css": "admin/css/base.6b517d0d5813.css", "admin/css/forms.css": "admin/css/forms.2003a066ae02.css", "admin/css/dashboard.css": "admin/css/dashboard.7ac78187c567.css", "admin/css/rtl.css": "admin/css/rtl.4c867197b256.css", "admin/css/changelists.css": "admin/css/changelists.f6dc691f8d62.css", "admin/css/login.css": "admin/css/login.a846c0e2ef65.css", "admin/css/widgets.css": "admin/css/widgets.5e372b41c483.css", "about/img/fire.jpg": "about/img/fire.a43156ac349a.jpg", "about/img/jade.jpg": "about/img/jade.fb7e88f68581.jpg", "about/fonts/glyphicons-halflings-regular.svg": "about/fonts/glyphicons-halflings-regular.89889688147b.svg", "about/fonts/glyphicons-halflings-regular.eot": "about/fonts/glyphicons-halflings-regular.f4769f9bdb74.eot", "about/fonts/glyphicons-halflings-regular.woff2": "about/fonts/glyphicons-halflings-regular.448c34a56d69.woff2", "about/fonts/glyphicons-halflings-regular.ttf": "about/fonts/glyphicons-halflings-regular.e18bbf611f2a.ttf", "about/fonts/glyphicons-halflings-regular.woff": "about/fonts/glyphicons-halflings-regular.fa2772327f55.woff", "about/js/bootstrap.js": "about/js/bootstrap.fb81549ee289.js", "about/js/npm.js": "about/js/npm.ccb7f3909e30.js", "about/js/bootstrap.min.js": "about/js/bootstrap.min.5869c96cc8f1.js", "about/css/bootstrap.css.map": "about/css/bootstrap.css.c7ffd8c7a285.map", "about/css/bootstrap-theme.min.css": "about/css/bootstrap-theme.min.ab6b02efeaf1.css", "about/css/cjap.css": "about/css/cjap.4d4ddddf87e4.css", "about/css/bootstrap-theme.min.css.map": "about/css/bootstrap-theme.min.css.5f587b800215.map", "about/css/bootstrap-theme.css": "about/css/bootstrap-theme.b9b46bcc4dad.css", "about/css/bootstrap.min.css.map": "about/css/bootstrap.min.css.35b79ebe0b78.map", "about/css/bootstrap.min.css": "about/css/bootstrap.min.5c7070ef655a.css", "about/css/bootstrap.css": "about/css/bootstrap.e7aa4e830a64.css", "about/css/bootstrap-theme.css.map": "about/css/bootstrap-theme.css.d6cc0a3c7532.map", "STATIC_README.md": "STATIC_README.606ae1b8310a.md"}, "version": "1.0"}